braandket/__init__.py
braandket/backend/__init__.py
braandket/backend/backend.py
braandket/backend/default.py
braandket/backend/numpy_backend.py
braandket/backend/tensorflow_backend.py
braandket/space/__init__.py
braandket/space/hilbert_space.py
braandket/space/num_space.py
braandket/space/space.py
braandket/tensor/__init__.py
braandket/tensor/operations.py
braandket/tensor/special.py
braandket/tensor/tensor.py
braandket/utils/__init__.py
braandket/utils/utils.py
BraAndKet-0.8.6.post1.dist-info/LICENSE
BraAndKet-0.8.6.post1.dist-info/METADATA
BraAndKet-0.8.6.post1.dist-info/WHEEL
BraAndKet-0.8.6.post1.dist-info/top_level.txt
BraAndKet-0.8.6.post1.dist-info/RECORD
