Metadata-Version: 2.1
Name: BraAndKet
Version: 0.8.6.post1
Summary: BraAndKet is a library for numeral calculations of discrete quantum systems.
Author-email: Zheng Keli <zhengkeli2009@126.com>
Project-URL: repository, https://github.com/ZhengKeli/BraAndKet
Classifier: Programming Language :: Python :: 3
Classifier: License :: OSI Approved :: MIT License
Classifier: Operating System :: OS Independent
Requires-Python: >=3.8
License-File: LICENSE
Requires-Dist: numpy
Provides-Extra: tf
Requires-Dist: tensorflow ; extra == 'tf'
